odoo/addons/web_widget_one2many_tree_line_duplicate/README.rst
odoo/addons/web_widget_one2many_tree_line_duplicate/__init__.py
odoo/addons/web_widget_one2many_tree_line_duplicate/__manifest__.py
odoo/addons/web_widget_one2many_tree_line_duplicate/i18n/it.po
odoo/addons/web_widget_one2many_tree_line_duplicate/i18n/web_widget_one2many_tree_line_duplicate.pot
odoo/addons/web_widget_one2many_tree_line_duplicate/readme/CONTRIBUTORS.md
odoo/addons/web_widget_one2many_tree_line_duplicate/readme/DESCRIPTION.md
odoo/addons/web_widget_one2many_tree_line_duplicate/readme/ROADMAP.md
odoo/addons/web_widget_one2many_tree_line_duplicate/readme/USAGE.md
odoo/addons/web_widget_one2many_tree_line_duplicate/static/description/icon.png
odoo/addons/web_widget_one2many_tree_line_duplicate/static/description/index.html
odoo/addons/web_widget_one2many_tree_line_duplicate/static/src/list/list_renderer.esm.js
odoo/addons/web_widget_one2many_tree_line_duplicate/static/src/list/list_renderer.xml
odoo_addon_web_widget_one2many_tree_line_duplicate-18.0.1.0.1.2.dist-info/METADATA
odoo_addon_web_widget_one2many_tree_line_duplicate-18.0.1.0.1.2.dist-info/WHEEL
odoo_addon_web_widget_one2many_tree_line_duplicate-18.0.1.0.1.2.dist-info/top_level.txt
odoo_addon_web_widget_one2many_tree_line_duplicate-18.0.1.0.1.2.dist-info/RECORD
